nato/__init__.py
nato/__main__.py
nato-1.0.0.dist-info/LICENSE.txt
nato-1.0.0.dist-info/METADATA
nato-1.0.0.dist-info/WHEEL
nato-1.0.0.dist-info/entry_points.txt
nato-1.0.0.dist-info/top_level.txt
nato-1.0.0.dist-info/RECORD
