Metadata-Version: 2.1
Name: nato
Version: 1.0.0
Summary: Are completely arbitrary words better than 1 letter variables?  Let's find out together!
Home-page: http://github.com/steder/nato
Author: Mike Steder
Author-email: steder@gmail.com
License: MIT
Platform: UNKNOWN
Classifier: Development Status :: 3 - Alpha
Classifier: Intended Audience :: Developers
Classifier: License :: OSI Approved :: MIT License
Classifier: Programming Language :: Python
Requires-Dist: astor
